README.md
setup.py
amazon_search_results_scraper/__init__.py
amazon_search_results_scraper.egg-info/PKG-INFO
amazon_search_results_scraper.egg-info/SOURCES.txt
amazon_search_results_scraper.egg-info/dependency_links.txt
amazon_search_results_scraper.egg-info/requires.txt
amazon_search_results_scraper.egg-info/top_level.txt