Metadata-Version: 2.1
Name: amazon-search-results-scraper
Version: 1.0.1
Summary: A python library to search keyword and scrape search results data from amazon.
Home-page: https://amazon-api.datakund.com/en/latest/
Author: DataKund
Author-email: datakund@gmail.com
License: Apache License 2.0
Keywords: amazon python bot_studio scraper web-scraping product search-results search keyword
Platform: UNKNOWN
